waferview/__init__.py
waferview/__main__.py
waferview/wafermap.py
waferview/gui/__init__.py
waferview/gui/constants.py
waferview/gui/gui.py
waferview/gui/semimap.py
wafer_view-1.1.0.dist-info/LICENSE
wafer_view-1.1.0.dist-info/METADATA
wafer_view-1.1.0.dist-info/WHEEL
wafer_view-1.1.0.dist-info/entry_points.txt
wafer_view-1.1.0.dist-info/top_level.txt
wafer_view-1.1.0.dist-info/RECORD
