Metadata-Version: 2.1
Name: wafer-view
Version: 1.1.0
Summary: An open source semi.org xml wafer viewer
Author-email: Kevin Fronczak <kfronczak@gmail.com>
Maintainer-email: Kevin Fronczak <kfronczak@gmail.com>
License: Apache License
Project-URL: Source Code, https://github.com/fronzbot/wafer-viewer
Project-URL: Bug Reports, https://github.com/fronzbot/wafer-viewer/issues
Platform: any
Classifier: License :: OSI Approved :: Apache Software License
Classifier: Operating System :: MacOS :: MacOS X
Classifier: Operating System :: Microsoft :: Windows :: Windows 11
Classifier: Programming Language :: Python :: 3.9
Classifier: Programming Language :: Python :: 3.10
Classifier: Programming Language :: Python :: 3.11
Classifier: Programming Language :: Python :: 3.12
Classifier: Topic :: Scientific/Engineering :: Visualization
Requires-Python: >=3.9.0
License-File: LICENSE
Requires-Dist: xmltodict (==0.13.0)
Requires-Dist: wxPython (==4.2.1)
